mlpipe/MLpipeBuildinJob.py
mlpipe/__init__.py
mlpipe/forms.py
mlpipe/job_utils.py
mlpipe/mlpipe_utils.py
mlpipe/models.py
mlpipe/pipe_utils.py
mlpipe/settings.py
mlpipe/urls.py
mlpipe/views.py
mlpipe/wsgi.py
mlpipe/apps/__init__.py
mlpipe/apps/core/__init__.py
mlpipe/apps/core/module/__init__.py
mlpipe/apps/core/module/create_local_folder.py
mlpipe/apps/core/module/create_local_folder.yaml
mlpipe/apps/core/module/downsample_by_line.py
mlpipe/apps/core/module/downsample_by_line.yaml
mlpipe/apps/core/module/find_min.py
mlpipe/apps/core/module/find_min.yaml
mlpipe/apps/core/module/kaggle_download.yaml
mlpipe/apps/core/module/kaggle_submission.yaml
mlpipe/apps/core/module/split_file_by_line.py
mlpipe/apps/core/module/split_file_by_line.yaml
mlpipe/apps/core/module/unzip.yaml
mlpipe/apps/core/module/upload_to_s3.py
mlpipe/apps/core/module/upload_to_s3.yaml
mlpipe/apps/core/pipe/test_download.yaml
mlpipe/apps/core/pipe/test_submission.yaml
mlpipe/management/__init__.py
mlpipe/management/commands/__init__.py
mlpipe/management/commands/addapp.py
mlpipe/management/commands/canceljob.py
mlpipe/management/commands/cancelpipe.py
mlpipe/management/commands/cleanjob.py
mlpipe/management/commands/config.py
mlpipe/management/commands/create_yaml.py
mlpipe/management/commands/deletepipe.py
mlpipe/management/commands/getmd5.py
mlpipe/management/commands/init.py
mlpipe/management/commands/joblog.py
mlpipe/management/commands/listexp.py
mlpipe/management/commands/listjob.py
mlpipe/management/commands/listmodule.py
mlpipe/management/commands/listpipe.py
mlpipe/management/commands/runall.py
mlpipe/management/commands/runjob.py
mlpipe/management/commands/runpipe.py
mlpipe/management/commands/startpipe.py
mlpipe/management/commands/viewjob.py
mlpipe/management/commands/viewmodule.py
mlpipe-0.1.17.data/scripts/ml
mlpipe-0.1.17.dist-info/DESCRIPTION.rst
mlpipe-0.1.17.dist-info/METADATA
mlpipe-0.1.17.dist-info/RECORD
mlpipe-0.1.17.dist-info/WHEEL
mlpipe-0.1.17.dist-info/metadata.json
mlpipe-0.1.17.dist-info/top_level.txt
