Metadata-Version: 2.0
Name: mlpipe
Version: 0.1.17
Summary: A toolkit to manage machine learning libraries.
Home-page: https://github.com/LongbinChen/mlpipe
Author: Longbin Chen
Author-email: lbchen@gmail.com
License: LICENSE
Platform: UNKNOWN
Requires-Dist: astroid (==1.6.1)
Requires-Dist: backports.functools-lru-cache (==1.5)
Requires-Dist: configparser (==3.5.0)
Requires-Dist: Django (==1.11.10)
Requires-Dist: django-bootstrap-ui (==0.5.1)
Requires-Dist: django-bootstrap3 (==9.1.0)
Requires-Dist: django-tag-parser (==2.1)
Requires-Dist: dominate (==2.1.17)
Requires-Dist: enum34 (==1.1.6)
Requires-Dist: futures
Requires-Dist: isort (==4.3.3)
Requires-Dist: lazy-object-proxy (==1.3.1)
Requires-Dist: mccabe (==0.6.1)
Requires-Dist: pycodestyle (==2.3.1)
Requires-Dist: pytz (==2018.3)
Requires-Dist: PyYAML (==3.12)
Requires-Dist: singledispatch (==3.4.0.3)
Requires-Dist: six (==1.11.0)
Requires-Dist: termcolor (==1.1.0)
Requires-Dist: wrapt (==1.10.11)
